MANIFEST.in
README.rst
setup.py
Bravo.egg-info/PKG-INFO
Bravo.egg-info/SOURCES.txt
Bravo.egg-info/dependency_links.txt
Bravo.egg-info/requires.txt
Bravo.egg-info/top_level.txt
bravo/__init__.py
bravo/amp.py
bravo/blocks.py
bravo/chunk.py
bravo/config.py
bravo/encodings.py
bravo/entity.py
bravo/errors.py
bravo/ibravo.py
bravo/irc.py
bravo/location.py
bravo/mobmanager.py
bravo/motd.py
bravo/nbt.py
bravo/plugin.py
bravo/region.py
bravo/remote.py
bravo/service.py
bravo/simplex.py
bravo/stdio.py
bravo/weather.py
bravo/web.py
bravo/world.py
bravo/beta/__init__.py
bravo/beta/factory.py
bravo/beta/packets.py
bravo/beta/protocol.py
bravo/beta/recipes.py
bravo/beta/structures.py
bravo/geometry/__init__.py
bravo/geometry/section.py
bravo/infini/__init__.py
bravo/infini/factory.py
bravo/infini/packets.py
bravo/infini/protocol.py
bravo/inventory/__init__.py
bravo/inventory/slots.py
bravo/inventory/windows.py
bravo/plugins/__init__.py
bravo/plugins/automatons.py
bravo/plugins/beds.py
bravo/plugins/build_hooks.py
bravo/plugins/compound_hooks.py
bravo/plugins/dig_hooks.py
bravo/plugins/door.py
bravo/plugins/fertilizer.py
bravo/plugins/generators.py
bravo/plugins/paintings.py
bravo/plugins/physics.py
bravo/plugins/redstone.py
bravo/plugins/teleport.py
bravo/plugins/tracks.py
bravo/plugins/web.py
bravo/plugins/window_hooks.py
bravo/plugins/worldedit.py
bravo/plugins/commands/__init__.py
bravo/plugins/commands/common.py
bravo/plugins/commands/debug.py
bravo/plugins/commands/warp.py
bravo/plugins/serializers/__init__.py
bravo/plugins/serializers/beta.py
bravo/plugins/serializers/memory.py
bravo/policy/__init__.py
bravo/policy/dig.py
bravo/policy/packs.py
bravo/policy/seasons.py
bravo/policy/recipes/__init__.py
bravo/policy/recipes/blueprints.py
bravo/policy/recipes/ingredients.py
bravo/terrain/__init__.py
bravo/terrain/trees.py
bravo/tests/__init__.py
bravo/tests/test_blocks.py
bravo/tests/test_chunk.py
bravo/tests/test_config.py
bravo/tests/test_entity.py
bravo/tests/test_irc.py
bravo/tests/test_location.py
bravo/tests/test_nbt.py
bravo/tests/test_plugin.py
bravo/tests/test_region.py
bravo/tests/test_simplex.py
