Metadata-Version: 1.0
Name: Bravo
Version: 2.0
Summary: Minecraft server and utilities
Home-page: http://github.com/MostAwesomeDude/bravo
Author: Corbin Simpson
Author-email: MostAwesomeDude@gmail.com
License: MIT/X11
Platform: UNKNOWN
